{
  "trophy1": {
    "name": "Легенда Цусимы",
    "emoji": "🗡️",
    "description": [
      "Легенда Цусимы — получите платиновый трофей в игре Ghost of Tsushima.",
      "Доказательство: Скриншот с видимым PSN и платиновым призом."
    ]
  },
  "trophy2": {
    "name": "Легенда Эдзо",
    "emoji": "🏔",
    "description": [
      "Легенда Эдзо — получите платиновый трофей в Ghost of Yōtei.",
      "Доказательство: Скриншот с видимым PSN и платиновым призом."
    ]
  },
  "trophy3": {
    "name": "Легенда Хуёв",
    "emoji": "🏔",
    "description": [
      "Легенда Эдзо — получите платиновый трофей в Ghost of Yōtei.",
      "Доказательство: Скриншот с видимым PSN и платиновым призом."
    ]
  },
  "trophy4": {
    "name": "Легенда Мандавошек",
    "emoji": "🏔",
    "description": [
      "Легенда Эдзо — получите платиновый трофей в Ghost of Yōtei.",
      "Доказательство: Скриншот с видимым PSN и платиновым призом."
    ]
  },
  "trophy5": {
    "name": "Легенда Жопосранчиков",
    "emoji": "🏔",
    "description": [
      "Легенда Эдзо — получите платиновый трофей в Ghost of Yōtei.",
      "Доказательство: Скриншот с видимым PSN и платиновым призом."
    ]
  },
  "trophy6": {
    "name": "Легенда Легенд",
    "emoji": "🏔",
    "description": [
      "Легенда Эдзо — получите платиновый трофей в Ghost of Yōtei.",
      "Доказательство: Скриншот с видимым PSN и платиновым призом."
    ]
  },
  "trophy7": {
    "name": "Легенда Самураев",
    "emoji": "🏔",
    "description": [
      "Легенда Эдзо — получите платиновый трофей в Ghost of Yōtei.",
      "Доказательство: Скриншот с видимым PSN и платиновым призом."
    ]
  },
  "trophy8": {
    "name": "Легенда Самураев",
    "emoji": "🏔",
    "description": [
      "Легенда Эдзо — получите платиновый трофей в Ghost of Yōtei.",
      "Доказательство: Скриншот с видимым PSN и платиновым призом."
    ]
  },
  "trophy9": {
    "name": "Легенда Самураев",
    "emoji": "🏔",
    "description": [
      "Легенда Эдзо — получите платиновый трофей в Ghost of Yōtei.",
      "Доказательство: Скриншот с видимым PSN и платиновым призом."
    ]
  },
  "trophy10": {
    "name": "Легенда Самураев",
    "emoji": "🏔",
    "description": [
      "Легенда Эдзо — получите платиновый трофей в Ghost of Yōtei.",
      "Доказательство: Скриншот с видимым PSN и платиновым призом."
    ]
  }
}
